pbite/__init__.py
pbite/main.py
pbite/parser.py
pbite-0.0.2.dist-info/METADATA
pbite-0.0.2.dist-info/WHEEL
pbite-0.0.2.dist-info/entry_points.txt
pbite-0.0.2.dist-info/RECORD
