Metadata-Version: 2.1
Name: pbite
Version: 0.0.2
Summary: `ls` for project metadata
Author-email: Chris Pryer <cnpryer@gmail.com>
Requires-Python: >=3.8
Requires-Dist: rtoml>=0.9.0
